JT/ActivationFunctions.py
JT/CPI.xlsx
JT/Clustering.py
JT/Gradients.py
JT/Initializers.py
JT/Interactions.py
JT/KNearest.py
JT/Layers.py
JT/LossFunctions.py
JT/MakeSet.py
JT/Models.py
JT/NNet.py
JT/Optimizers.py
JT/PCA.py
JT/Timer.py
JT/Transforms.py
JT/Trees.py
JT/Utils.py
JT/__init__.py
JT/misc.py
JT/setup.py
JT/Torch/RNN.py
JT/Torch/Utils.py
JT/Torch/__init__.py
JT/Torch/cuda/Utils.py
JT/Torch/cuda/__init__.py
JT_Techfield-0.0.11.dist-info/LICENSE
JT_Techfield-0.0.11.dist-info/METADATA
JT_Techfield-0.0.11.dist-info/WHEEL
JT_Techfield-0.0.11.dist-info/top_level.txt
JT_Techfield-0.0.11.dist-info/RECORD
