Metadata-Version: 2.1
Name: JT-Techfield
Version: 0.0.11
Summary: My Data Science Module
Home-page: UNKNOWN
Author: Jacob Thompson
Author-email: jacob.thompson@techfield.us
License: UNKNOWN
Platform: UNKNOWN
Classifier: Programming Language :: Python :: 3
Classifier: License :: OSI Approved :: MIT License
Classifier: Operating System :: OS Independent
Requires-Python: >=3
Requires-Dist: numpy
Requires-Dist: matplotlib
Requires-Dist: pandas
Requires-Dist: scipy
Requires-Dist: torch
